.gitignore
.pre-commit-config.yaml
.travis.yml
CHANGES.rst
LICENSE
README.rst
setup.cfg
setup.py
tox.ini
src/lookuper/__init__.py
src/lookuper.egg-info/PKG-INFO
src/lookuper.egg-info/SOURCES.txt
src/lookuper.egg-info/dependency_links.txt
src/lookuper.egg-info/top_level.txt
tests/conftest.py
tests/test_lookuper.py